{
  "contract-interaction-with-viem": {
    "tutorial": "# Contract Interaction with Viem\n\n## Introduction\nThis example app demonstrates how to interact with Immutable smart contracts using the Viem library. It focuses on performing batch minting operations for ERC721 tokens on the Immutable zkEVM network. The example showcases two different batch minting approaches: minting by specific token IDs and minting by quantity.\n\n## Features Overview\n- Connecting to the Immutable zkEVM network using Viem\n- Interacting with ERC721 contracts using the `@imtbl/contracts` ABI\n- Checking permissions before executing contract functions\n- Batch minting ERC721 tokens by specific IDs\n- Batch minting ERC721 tokens by quantity\n\n## SDK Integration Details\n\n### Connecting to Immutable zkEVM Network\n**Link**: [batch-mint-erc721-by-id.ts](https://github.com/immutable/ts-immutable-sdk/blob/main/examples/contracts/contract-interaction-with-viem/batch-mint-erc721-by-id.ts#L28-L37)\n\n**Feature Name**: Network Connection with Viem\n\n**Implementation**:\n```typescript\nconst immutableTestnet = defineChain({\n  id: 13473,\n  name: 'imtbl-zkevm-testnet',\n  nativeCurrency: { name: 'IMX', symbol: 'IMX', decimals: 18 },\n  rpcUrls: {\n    default: {\n      http: ['https://rpc.testnet.immutable.com'],\n    },\n  },\n});\n\nconst walletClient = createWalletClient({\n  chain: immutableTestnet,\n  transport: http(),\n  account: privateKeyToAccount(privateKey),\n});\n```\n\n**Explanation**: This code defines the Immutable zkEVM testnet network configuration and creates a wallet client. The `defineChain` function from Viem allows you to specify the network details, including the chain ID, name, native currency, and RPC endpoints. The wallet client is created using the network configuration, an HTTP transport, and an account derived from a private key.\n\n### Contract Interaction Setup\n**Link**: [batch-mint-erc721-by-id.ts](https://github.com/immutable/ts-immutable-sdk/blob/main/examples/contracts/contract-interaction-with-viem/batch-mint-erc721-by-id.ts#L39-L43)\n\n**Feature Name**: Contract Instance Creation\n\n**Implementation**:\n```typescript\nconst contract = getContract({\n  address: contractAddress,\n  abi: ImmutableERC721Abi,\n  client: walletClient,\n});\n```\n\n**Explanation**: This code creates a contract instance using Viem's `getContract` function. It requires the contract address, ABI, and wallet client. The ABI is imported from the `@imtbl/contracts` package, which provides the interface definitions for Immutable's smart contracts. The contract instance can be used to call read and write functions on the contract.\n\n### Permission Checking\n**Link**: [batch-mint-erc721-by-id.ts](https://github.com/immutable/ts-immutable-sdk/blob/main/examples/contracts/contract-interaction-with-viem/batch-mint-erc721-by-id.ts#L47-L60)\n\n**Feature Name**: Role-Based Access Control\n\n**Implementation**:\n```typescript\nconst minterRole = await contract.read.MINTER_ROLE();\n\nconst hasMinterRole = await contract.read.hasRole([\n  minterRole,\n  walletClient.account.address,\n]);\n\nif (!hasMinterRole) {\n  // Handle scenario without permissions...\n  console.log('Account doesnt have permissions to mint.');\n  return Promise.reject(\n    new Error('Account doesnt have permissions to mint.'),\n  );\n}\n```\n\n**Explanation**: Before attempting to mint tokens, this code checks if the wallet has the required permissions. It first retrieves the `MINTER_ROLE` constant from the contract, then uses the `hasRole` function to determine if the wallet address has that role. If the wallet doesn't have the required role, the function returns an error, preventing unauthorized minting operations.\n\n### Batch Minting by ID\n**Link**: [batch-mint-erc721-by-id.ts](https://github.com/immutable/ts-immutable-sdk/blob/main/examples/contracts/contract-interaction-with-viem/batch-mint-erc721-by-id.ts#L62-L64)\n\n**Feature Name**: Batch Minting ERC721 Tokens by Specific IDs\n\n**Implementation**:\n```typescript\nconst txHash = await contract.write.mintBatch([requests]);\n\nconsole.log(`txHash: ${txHash}`);\nreturn txHash;\n```\n\n**Explanation**: This code calls the `mintBatch` function on the contract to mint multiple ERC721 tokens with specific token IDs. The `requests` parameter is an array of objects, each containing a recipient address (`to`) and an array of token IDs (`tokenIds`) to mint for that recipient. The function returns the transaction hash, which can be used to track the transaction status.\n\n### Batch Minting by Quantity\n**Link**: [batch-mint-erc721-by-quantity.ts](https://github.com/immutable/ts-immutable-sdk/blob/main/examples/contracts/contract-interaction-with-viem/batch-mint-erc721-by-quantity.ts#L62-L64)\n\n**Feature Name**: Batch Minting ERC721 Tokens by Quantity\n\n**Implementation**:\n```typescript\nconst txHash = await contract.write.mintBatchByQuantity([mints]);\n\nconsole.log(`txHash: ${txHash}`);\nreturn txHash;\n```\n\n**Explanation**: This code calls the `mintBatchByQuantity` function on the contract to mint multiple ERC721 tokens by specifying the quantity to mint. The `mints` parameter is an array of objects, each containing a recipient address (`to`) and a quantity (`quantity`) of tokens to mint for that recipient. The function returns the transaction hash. Unlike the `mintBatch` function that requires specific token IDs, this function automatically assigns sequential token IDs.\n\n## Running the App\n\nThis example demonstrates how to use the code in your own application. To implement this:\n\n1. Visit [GitHub Repository](https://github.com/immutable/ts-immutable-sdk/tree/main/examples/contracts/contract-interaction-with-viem) for full source code.\n\n### Prerequisites\n- Node.js and pnpm installed\n- An Immutable Passport account and project set up through [Immutable Hub](https://hub.immutable.com)\n- A deployed ERC721 contract on Immutable zkEVM\n- A private key with MINTER_ROLE permission on the contract\n\n### Steps to Use in Your Project\n\n1. Install the required dependencies:\n   ```bash\n   pnpm add viem @imtbl/contracts\n   ```\n\n2. Set up your environment variables for `PRIVATE_KEY` and `CONTRACT_ADDRESS`.\n\n3. Import the functions into your project:\n   ```typescript\n   import { batchMintERC721ByID, batchMintERC721ByQuantity } from './path-to-example';\n   ```\n\n4. Call the functions with the appropriate parameters:\n   ```typescript\n   // For minting by ID\n   const requests = [\n     {\n       to: '0xRecipientAddress1',\n       tokenIds: [BigInt(1), BigInt(2)],\n     },\n     {\n       to: '0xRecipientAddress2',\n       tokenIds: [BigInt(3), BigInt(4)],\n     },\n   ];\n   \n   const txHash = await batchMintERC721ByID(privateKey, contractAddress, requests);\n\n   // OR for minting by quantity\n   const mints = [\n     {\n       to: '0xRecipientAddress1',\n       quantity: BigInt(3),\n     },\n     {\n       to: '0xRecipientAddress2',\n       quantity: BigInt(3),\n     },\n   ];\n   \n   const txHash = await batchMintERC721ByQuantity(privateKey, contractAddress, mints);\n   ```\n\n## Summary\n\nThis example demonstrates how to interact with Immutable smart contracts using Viem, focusing on batch minting operations for ERC721 tokens. The example showcases two approaches to batch minting: one that allows you to specify exact token IDs and another that automatically assigns IDs based on quantity.\n\nKey takeaways:\n- Viem provides a clean and type-safe way to interact with Ethereum/zkEVM contracts\n- Always check permissions before attempting to perform restricted operations\n- Batch operations can significantly reduce gas costs by combining multiple transactions\n- The `@imtbl/contracts` package provides helpful ABIs for interacting with Immutable's standard contracts ",
    "metadata": {
      "title": "Contract Interaction with Viem",
      "description": "Example demonstrating how to interact with Immutable ERC721 contracts using Viem for batch minting operations on Immutable zkEVM",
      "keywords": [
        "Immutable",
        "SDK",
        "ERC721",
        "Viem",
        "BatchMint",
        "zkEVM",
        "Contracts"
      ],
      "tech_stack": [
        "TypeScript",
        "Viem",
        "@imtbl/contracts"
      ],
      "product": "Contracts",
      "programming_language": "TypeScript"
    }
  }
}